epydemiology/__init__.py
epydemiology/phjCalculateProportions.py
epydemiology/phjCalculateProportionsORIG.py
epydemiology/phjCleanData.py
epydemiology/phjCleanUKPostcodes.py
epydemiology/phjCleanUKPostcodesORIG.py
epydemiology/phjExploreData.py
epydemiology/phjExtFuncs.py
epydemiology/phjGetDBData.py
epydemiology/phjGetData.py
epydemiology/phjMatrices.py
epydemiology/phjMiscFuncs.py
epydemiology/phjPrelimPrepForSelectData.py
epydemiology/phjRROR.py
epydemiology/phjSelectData.py
epydemiology/phjTestFunctionParameters.py
epydemiology-0.1.30.dist-info/DESCRIPTION.rst
epydemiology-0.1.30.dist-info/METADATA
epydemiology-0.1.30.dist-info/RECORD
epydemiology-0.1.30.dist-info/WHEEL
epydemiology-0.1.30.dist-info/metadata.json
epydemiology-0.1.30.dist-info/top_level.txt
